doteval/__init__.py
doteval/_version.py
doteval/cli.py
doteval/core.py
doteval/datasets.py
doteval/evaluators.py
doteval/fixtures.py
doteval/metrics.py
doteval/models.py
doteval/plugin.py
doteval/progress.py
doteval/providers.py
doteval/runners.py
doteval/sessions.py
doteval/utils.py
doteval/concurrency/__init__.py
doteval/concurrency/adaptive.py
doteval/concurrency/async_sequential.py
doteval/concurrency/batch.py
doteval/concurrency/sequential.py
doteval/concurrency/sliding_window.py
doteval/storage/__init__.py
doteval/storage/base.py
doteval/storage/json.py
doteval/storage/sqlite.py
dottxt_eval-0.22.0.dist-info/METADATA
dottxt_eval-0.22.0.dist-info/WHEEL
dottxt_eval-0.22.0.dist-info/entry_points.txt
dottxt_eval-0.22.0.dist-info/top_level.txt
dottxt_eval-0.22.0.dist-info/RECORD
