Metadata-Version: 2.4
Name: dottxt-eval
Version: 0.22.0
Summary: Simple and robust LLM evaluations
Author: .txt
Project-URL: repository, https://github.com/dottxt-ai/doteval
Requires-Python: >=3.10
Requires-Dist: click
Requires-Dist: pytest
Requires-Dist: rich
Requires-Dist: jsonschema
Requires-Dist: tenacity
Provides-Extra: test
Requires-Dist: pytest-asyncio; extra == "test"
Requires-Dist: pre-commit; extra == "test"
Requires-Dist: pytest-cov; extra == "test"
Requires-Dist: coverage[toml]>=5.1; extra == "test"
Requires-Dist: diff-cover; extra == "test"
Requires-Dist: Pillow; extra == "test"
Provides-Extra: docs
Requires-Dist: mkdocs; extra == "docs"
Requires-Dist: mkdocstrings[python]; extra == "docs"
Requires-Dist: mkdocs-material[imaging]; extra == "docs"
Requires-Dist: mkdocs-mermaid2-plugin; extra == "docs"
Requires-Dist: mkdocs-section-index; extra == "docs"
Requires-Dist: mkdocs-git-committers-plugin-2; extra == "docs"
Requires-Dist: mkdocs-git-revision-date-localized-plugin; extra == "docs"
